{
  "category": "upgrades",
  "name": "Filtered Magnet (ItemStack)",
  "subtitle": "",
  "icon": "pedestals:coin/fmagnetitemstack",
  "sortnum": 8,
  "priority": true,
  "pages": [
    {
      "type": "crafting",
      "recipe": "pedestals:upgrades/fmagnetitemstack",
      "text": "$(l:https://github.com/Mowmaster/Pedestals/wiki/Filtered-Magnet-ItemStack)Wiki Link/$"
    },
    {
      "type": "text",
      "text": "Will gather up items in the area around it$(br)If they match the itemstack in the below inventory, It'll put them in the pedestal."
    }
  ]
}
